sv_shared/__init__.py
sv_shared/dataset_loader.py
sv_shared/parsers.py
sv_shared/rewards.py
sv_shared/rollout_logging.py
sv_shared/utils.py
sv_shared/weave_init.py
security_verifiers_utils-0.2.3.dist-info/METADATA
security_verifiers_utils-0.2.3.dist-info/WHEEL
security_verifiers_utils-0.2.3.dist-info/RECORD
