Metadata-Version: 2.4
Name: security-verifiers-utils
Version: 0.2.3
Summary: Shared utilities for Security Verifiers RL environments
Project-URL: Homepage, https://github.com/intertwine/security-verifiers
Project-URL: Repository, https://github.com/intertwine/security-verifiers
Project-URL: Issues, https://github.com/intertwine/security-verifiers/issues
Author-email: Intertwine AI <hello@intertwine.ai>
License: MIT
Keywords: alignment,reinforcement-learning,rl,security,utilities,verifiers
Classifier: Development Status :: 4 - Beta
Classifier: Intended Audience :: Developers
Classifier: Intended Audience :: Science/Research
Classifier: License :: OSI Approved :: MIT License
Classifier: Programming Language :: Python :: 3
Classifier: Programming Language :: Python :: 3.12
Classifier: Topic :: Scientific/Engineering :: Artificial Intelligence
Classifier: Topic :: Security
Requires-Python: >=3.12
Requires-Dist: datasets>=2.0.0
Requires-Dist: pandas>=2.0.0
Requires-Dist: verifiers>=0.1.9
Requires-Dist: weave>=0.51.0
Provides-Extra: dev
Requires-Dist: build>=1.0.0; extra == 'dev'
Requires-Dist: pytest>=7.0.0; extra == 'dev'
Requires-Dist: ruff>=0.12.11; extra == 'dev'
Requires-Dist: twine>=4.0.0; extra == 'dev'
